<?xml version="1.0" encoding="utf-8"?>
<Root>
  <R>
    <F>
      <S type="FormulaEditor.Symbols.SimpleSymbol" symbol="a" S="a" Type="1" Index="1" Level="0" DoubleValue="0" UlongValue="0" Italic="1" Bold="1" Sb="">
        <F />
      </S>
      <S type="FormulaEditor.Symbols.BinarySymbol" symbol="∖" S="AND" Type="3" Index="1" Level="0" DoubleValue="0" UlongValue="0" Italic="0" Bold="1" Sb="" />
      <S type="FormulaEditor.Symbols.SimpleSymbol" symbol="b" S="b" Type="1" Index="1" Level="0" DoubleValue="0" UlongValue="0" Italic="1" Bold="1" Sb="">
        <F />
      </S>
    </F>
  </R>
  <R>
    <F>
      <S type="FormulaEditor.Symbols.SimpleSymbol" symbol="a" S="a" Type="1" Index="1" Level="0" DoubleValue="0" UlongValue="0" Italic="1" Bold="1" Sb="">
        <F />
      </S>
      <S type="FormulaEditor.Symbols.BinarySymbol" symbol="∗" S="OR" Type="3" Index="1" Level="0" DoubleValue="0" UlongValue="0" Italic="0" Bold="1" Sb="" />
      <S type="FormulaEditor.Symbols.SimpleSymbol" symbol="b" S="b" Type="1" Index="1" Level="0" DoubleValue="0" UlongValue="0" Italic="1" Bold="1" Sb="">
        <F />
      </S>
    </F>
  </R>
  <R>
    <F>
      <S type="FormulaEditor.Symbols.SimpleSymbol" symbol="a" S="a" Type="1" Index="1" Level="0" DoubleValue="0" UlongValue="0" Italic="1" Bold="1" Sb="">
        <F />
      </S>
      <S type="FormulaEditor.Symbols.BinarySymbol" symbol="蠵" S="=&gt;" Type="3" Index="1" Level="0" DoubleValue="0" UlongValue="0" Italic="0" Bold="1" Sb="" />
      <S type="FormulaEditor.Symbols.SimpleSymbol" symbol="b" S="b" Type="1" Index="1" Level="0" DoubleValue="0" UlongValue="0" Italic="1" Bold="1" Sb="">
        <F />
      </S>
    </F>
  </R>
</Root>